CHANGELOG.txt
LICENCE.txt
MANIFEST.in
README.txt
setup.py
WebhookSender_py/__init__.py
WebhookSender_py.egg-info/PKG-INFO
WebhookSender_py.egg-info/SOURCES.txt
WebhookSender_py.egg-info/dependency_links.txt
WebhookSender_py.egg-info/requires.txt
WebhookSender_py.egg-info/top_level.txt