Metadata-Version: 2.1
Name: WebhookSender-py
Version: 1.0.0
Summary:  Discord Webhhook Sender   
Home-page: 
Author: 0xjohn
Classifier: License :: OSI Approved :: MIT License
Classifier: Programming Language :: Python :: 3
Classifier: Programming Language :: Python :: 3.9
License-File: LICENCE.txt
